seq_alignment/__init__.py
seq_alignment/global_similarity/__init__.py
seq_alignment/global_similarity/main.py
seq_alignment/helpers/__init__.py
seq_alignment/helpers/speed_test.py
seq_alignment/local_similarity/__init__.py
seq_alignment/local_similarity/main.py
seq_alignment/local_similarity/main_test.py
seq_alignment/tests/__init__.py
seq_alignment/tests/speed_testing.py
seq_alignment/tests/test_global_similarity.py
seq_alignment/tests/test_local_similarity.py
seq_alignment-1.0.0.dist-info/LICENSE
seq_alignment-1.0.0.dist-info/METADATA
seq_alignment-1.0.0.dist-info/WHEEL
seq_alignment-1.0.0.dist-info/top_level.txt
seq_alignment-1.0.0.dist-info/RECORD
