Metadata-Version: 2.1
Name: seq-alignment
Version: 1.0.0
Summary: A package to compute edit distance measurements and sequence alignments.
Home-page: https://github.com/ryanlstevens/seq_alignment
Author: Ryan Stevens and James Nesbit
Author-email: ryan.louis.stevens@gmail.com
License: UNKNOWN
Platform: UNKNOWN
Classifier: Programming Language :: Python :: 3
Classifier: License :: OSI Approved :: MIT License
Classifier: Operating System :: OS Independent
Requires-Python: >=3.6
